<?xml version="1.0" encoding="utf-8"?><toc><breadcrumbs><li><a href="73da3221-b42c-4d1a-bcfb-c020d277db47.htm">Docs</a></li><li><a href="47bcaf7c-c395-4df3-55a1-8a0843bb8c72.htm">Ode<wbr />Mod.<wbr />UI.<wbr />Ode<wbr />UISystem.<wbr />UIElements</a></li><li><a href="c18d652f-2e8b-d1cd-7ce8-f0ffb20bf72a.htm">UIInput<wbr />Box</a></li></breadcrumbs><tocItems><li><a id="e10aeeef-7748-17c7-a3b4-e9700b9a5385" href="e10aeeef-7748-17c7-a3b4-e9700b9a5385.htm">Constructor</a></li><li><a id="599da5f7-5986-2772-2f3f-7322ae341f4c" class="has-submenu" href="599da5f7-5986-2772-2f3f-7322ae341f4c.htm"><span data-tocFile="../toc/IDBR0GB0.xml" class="icon toggle" onclick="ToggleExpandCollapse(this); return false;"><i class="fa fa-angle-right"> </i></span>Properties</a><ul class="toc-menu is-hidden"> </ul></li><li><a id="6bd360fc-1884-3109-e652-e4bd963398b7" class="has-submenu" href="6bd360fc-1884-3109-e652-e4bd963398b7.htm"><span data-tocFile="../toc/IDCR0GB0.xml" class="icon toggle" onclick="ToggleExpandCollapse(this); return false;"><i class="fa fa-angle-right"> </i></span>Methods</a><ul class="toc-menu is-hidden"> </ul></li><li><a id="ff9934ac-fcb2-e80f-a4cb-0c9f6fc705e2" class="has-submenu" href="ff9934ac-fcb2-e80f-a4cb-0c9f6fc705e2.htm"><span data-tocFile="../toc/IDDR0GB0.xml" class="icon toggle" onclick="ToggleExpandCollapse(this); return false;"><i class="fa fa-angle-right"> </i></span>Fields</a><ul class="toc-menu is-hidden"> </ul></li></tocItems></toc>